MANIFEST.in
README
pysnipp.sh
setup.cfg
setup.py
pysnipp/__init__.py
pysnipp/__main__.py
pysnipp/controller.py
pysnipp/pysnipp.py
pysnipp/snippet.py
pysnipp.egg-info/PKG-INFO
pysnipp.egg-info/SOURCES.txt
pysnipp.egg-info/dependency_links.txt
pysnipp.egg-info/entry_points.txt
pysnipp.egg-info/requires.txt
pysnipp.egg-info/top_level.txt