Metadata-Version: 1.0
Name: pysnipp
Version: 0.5.1
Summary: console based snippet manager written in python3
Home-page: http://hauck-daniel.de/pysnipp
Author: Daniel Hauck
Author-email: daniel@hauck.it
License: GPL
Platform: UNKNOWN
